Django_Template_Preprocess-0.0.1.dist-info/METADATA
Django_Template_Preprocess-0.0.1.dist-info/RECORD
Django_Template_Preprocess-0.0.1.dist-info/WHEEL
Django_Template_Preprocess-0.0.1.dist-info/top_level.txt
template_preprocess/__init__.py
template_preprocess/admin.py
template_preprocess/apps.py
template_preprocess/models.py
template_preprocess/processor.py
template_preprocess/tests.py
template_preprocess/views.py
