Metadata-Version: 2.1
Name: Django-Template-Preprocess
Version: 0.0.1
Summary: Cut down on django template CPU time by doing work early.
Home-page: UNKNOWN
Author: UW-IT AXDD
Author-email: aca-it@uw.edu
License: Apache License, Version 2.0
Platform: UNKNOWN
Classifier: Intended Audience :: Developers
Classifier: License :: OSI Approved :: Apache Software License
Classifier: Operating System :: OS Independent
Classifier: Programming Language :: Python
Classifier: Programming Language :: Python :: 3.6
Requires-Dist: Django (<3.0,>2.1)
Requires-Dist: django-compressor
Requires-Dist: htmlmin
